markerpry/__about__.py
markerpry/__init__.py
markerpry/node.py
markerpry/parser.py
markerpry-0.4.0.dist-info/METADATA
markerpry-0.4.0.dist-info/WHEEL
markerpry-0.4.0.dist-info/licenses/LICENSE
markerpry-0.4.0.dist-info/RECORD
